gsw_xarray/__init__.py
gsw_xarray/_accessor.py
gsw_xarray/_arguments.py
gsw_xarray/_attributes.py
gsw_xarray/_check_funcs.py
gsw_xarray/_core.py
gsw_xarray/_function_utils.py
gsw_xarray/_names.py
gsw_xarray/_options.py
gsw_xarray/_units.py
gsw_xarray/_util.py
gsw_xarray/_util_module.py
gsw_xarray/conversions.py
gsw_xarray/density.py
gsw_xarray/energy.py
gsw_xarray/freezing.py
gsw_xarray/geostrophy.py
gsw_xarray/ice.py
gsw_xarray/stability.py
gsw_xarray/tests/__init__.py
gsw_xarray/tests/conftest.py
gsw_xarray/tests/test_accessor.py
gsw_xarray/tests/test_attrs.py
gsw_xarray/tests/test_gsw_xarray.py
gsw_xarray/tests/test_imports.py
gsw_xarray/tests/test_units.py
gsw_xarray/tests/test_utils.py
gsw_xarray/tests/test_version.py
gsw_xarray-0.5.0.dist-info/METADATA
gsw_xarray-0.5.0.dist-info/WHEEL
gsw_xarray-0.5.0.dist-info/licenses/LICENSE.rst
gsw_xarray-0.5.0.dist-info/RECORD
