Metadata-Version: 2.4
Name: gsw-xarray
Version: 0.5.0
Summary: Drop in wrapper for gsw which adds CF standard name and units attributes to xarray results
Project-URL: Repository, https://github.com/DocOtak/gsw-xarray
Project-URL: Documentation, https://gsw-xarray.readthedocs.io/
Author-email: Andrew Barna <abarna@gmail.com>, Romain Caneill <romain.caneill@ens-lyon.org>
License-Expression: BSD-3-Clause
License-File: LICENSE.rst
Requires-Python: >=3.11
Requires-Dist: cf-xarray>=0.8
Requires-Dist: gsw>=3.6.18; python_version <= '3.12'
Requires-Dist: gsw>=3.6.20; python_version == '3.13'
Requires-Dist: gsw>=3.6.20; python_version == '3.14'
Requires-Dist: xarray>=2023.09
Provides-Extra: pint
Requires-Dist: pint-xarray>=0.6; extra == 'pint'
Requires-Dist: pint>=0.24.4; extra == 'pint'
